<hello xmlns="urn:ietf:params:xml:ns:netconf:base:1.0">
  <capabilities>
    <capability>urn:ietf:params:netconf:base:1.0</capability>
    <capability>urn:ietf:params:netconf:base:1.1</capability>
  </capabilities>
</hello>
]]>]]>
#2105
<rpc message-id="m-0" xmlns="urn:ietf:params:xml:ns:netconf:base:1.0">
<edit-config>
<target>
<candidate/>
</target>
<error-option>rollback-on-error</error-option>
<config xmlns="urn:ietf:params:xml:ns:netconf:base:1.0">
    <interface-configurations xmlns="http://cisco.com/ns/yang/Cisco-IOS-XR-ifmgr-cfg">
        <interface-configuration>
            <active>act</active>
            <interface-name>MgmtEth0/0/CPU0/0</interface-name>
            <ipv4-network xmlns="http://cisco.com/ns/yang/Cisco-IOS-XR-ipv4-io-cfg">
                <addresses>
                    <primary>
                        <address>192.168.1.212</address>
                        <netmask>255.255.255.0</netmask>
                    </primary>
                </addresses>
            </ipv4-network>
        </interface-configuration>
        <interface-configuration>
            <active>act</active>
            <interface-name>GigabitEthernet0/0/0/0</interface-name>
            <shutdown></shutdown>
        </interface-configuration>
        <interface-configuration>
            <active>act</active>
            <interface-name>GigabitEthernet0/0/0/1</interface-name>
            <shutdown></shutdown>
        </interface-configuration>
        <interface-configuration>
            <active>act</active>
            <interface-name>GigabitEthernet0/0/0/2</interface-name>
            <shutdown></shutdown>
        </interface-configuration>
        <interface-configuration>
            <active>act</active>
            <interface-name>GigabitEthernet0/0/0/3</interface-name>
            <shutdown></shutdown>
        </interface-configuration>
        <interface-configuration>
            <active>act</active>
            <interface-name>GigabitEthernet0/0/0/4</interface-name>
            <shutdown></shutdown>
        </interface-configuration>
        <interface-configuration>
            <active>act</active>
            <interface-name>GigabitEthernet0/0/0/5</interface-name>
            <shutdown></shutdown>
        </interface-configuration>
    </interface-configurations>
</config>
</edit-config>
</rpc>
##

#95
<rpc xmlns="urn:ietf:params:xml:ns:netconf:base:1.0" message-id="101">
<commit></commit>
</rpc>
##